numericsinwords/__init__.py
numericsinwords/numbers_in_words.py
numericsinwords/time_in_words.py
numericsinwords-1.0.dist-info/METADATA
numericsinwords-1.0.dist-info/WHEEL
numericsinwords-1.0.dist-info/licence.txt
numericsinwords-1.0.dist-info/top_level.txt
numericsinwords-1.0.dist-info/RECORD
