Metadata-Version: 2.1
Name: numericsinwords
Version: 1.0
Summary: Provide number or time and get them in words
Home-page: UNKNOWN
Author: Turyamusiima Dismas
License: UNKNOWN
Platform: UNKNOWN
License-File: licence.txt
